polar_analyzer/__init__.py
polar_analyzer/polar_analyzer.py
polar_analyzer/polaranalyzer.py
polar_analyzer-1.0.dist-info/DESCRIPTION.rst
polar_analyzer-1.0.dist-info/METADATA
polar_analyzer-1.0.dist-info/RECORD
polar_analyzer-1.0.dist-info/WHEEL
polar_analyzer-1.0.dist-info/metadata.json
polar_analyzer-1.0.dist-info/top_level.txt
