Metadata-Version: 2.0
Name: polar-analyzer
Version: 1.0
Summary: maps positive and negative semantic values to words in a string or a text file.
Home-page: http://github.com/sherifEwis/polar_analyzer/
Author: Flying Circus
Author-email: sherifewis@tickletock.com
License: MIT
Platform: UNKNOWN
Requires-Dist: matplotlib
Requires-Dist: nltk
Requires-Dist: statistics
